sparc.configuration-0.0.2-nspkg.pth
sparc/configuration/__init__.py
sparc/configuration/configure.zcml
sparc/configuration/events.py
sparc/configuration/ftesting.zcml
sparc/configuration/interfaces.py
sparc/configuration/testing.py
sparc/configuration/container/__init__.py
sparc/configuration/container/application.py
sparc/configuration/container/configure.zcml
sparc/configuration/container/container.py
sparc/configuration/container/interfaces.py
sparc/configuration/container/values.py
sparc/configuration/container/tests/__init__.py
sparc/configuration/container/tests/test_container.py
sparc/configuration/container/tests/test_values.py
sparc/configuration/container/zcml/__init__.py
sparc/configuration/container/zcml/configure.zcml
sparc/configuration/container/zcml/interfaces.py
sparc/configuration/container/zcml/zcml.py
sparc/configuration/container/zcml/tests/__init__.py
sparc/configuration/container/zcml/tests/test_zcml.py
sparc/configuration/xml/__init__.py
sparc/configuration/xml/config.py
sparc/configuration/xml/configure.zcml
sparc/configuration/xml/interfaces.py
sparc/configuration/xml/tests/__init__.py
sparc/configuration/xml/tests/test_config.py
sparc/configuration/yaml/__init__.py
sparc/configuration/yaml/configure.zcml
sparc/configuration/yaml/documents.py
sparc/configuration/yaml/interfaces.py
sparc/configuration/yaml/tests/__init__.py
sparc/configuration/yaml/tests/test_documents.py
sparc/configuration/zcml/__init__.py
sparc/configuration/zcml/configure.py
sparc.configuration-0.0.2.dist-info/DESCRIPTION.rst
sparc.configuration-0.0.2.dist-info/METADATA
sparc.configuration-0.0.2.dist-info/RECORD
sparc.configuration-0.0.2.dist-info/WHEEL
sparc.configuration-0.0.2.dist-info/entry_points.txt
sparc.configuration-0.0.2.dist-info/metadata.json
sparc.configuration-0.0.2.dist-info/namespace_packages.txt
sparc.configuration-0.0.2.dist-info/top_level.txt
